<?xml version="1.0" encoding="utf-8"?>
<annotation>
	<folder>None</folder>
	<filename>827</filename>
	<source>
		<dataset>vidvrd</dataset>
	</source>
	<size>
		<width>1280</width>
		<height>720</height>
		<depth>3</depth>
	</size>
	<object>
		<trackid>0</trackid>
		<name>dog</name>
		<bndbox>
			<xmin>823</xmin>
			<ymin>197</ymin>
			<xmax>1217</xmax>
			<ymax>716</ymax>
		</bndbox>
		<occluded>0</occluded>
		<generated>0</generated>
	</object>
	<object>
		<trackid>1</trackid>
		<name>antelope</name>
		<bndbox>
			<xmin>528</xmin>
			<ymin>40</ymin>
			<xmax>769</xmax>
			<ymax>417</ymax>
		</bndbox>
		<occluded>0</occluded>
		<generated>0</generated>
	</object>
</annotation>
